{
  "last_checked": "2026-07-13T00:19:00+02:00",
  "scraping_status": "partial",
  "status_note": "LeBonCoin bloque (DataDome+captcha, page vide). BackMarket charge mais categorie mac-studio-reconditionne ne renvoie aucune donnee produit exploitable (page generique, ID de categorie possiblement obsolete). Vinted fonctionne et renvoie de vraies donnees mais aucun match reel : recherches polluees par des produits MAC cosmetics, et les Mac mini/Studio Apple presents sont tous en dessous de 64Go RAM (ex: Mac Mini M4 24Go/2To a 1950EUR - RAM insuffisante).",
  "target": {
    "model": "Mac Studio / Mac mini reconditionné ou occasion",
    "specs": "≥ 64 Go RAM · ≥ 1 To SSD · puce Max/Ultra/Pro · ≤ 2520 € TTC",
    "platforms": [
      "LeBonCoin",
      "BackMarket",
      "Vinted"
    ]
  },
  "listings": [
    {
      "id": "lbc-3226340061",
      "title": "Mac Studio M2 Ultra — 64 Go RAM, 1 To SSD",
      "price": "2500 € TTC",
      "platform": "LeBonCoin",
      "url": "https://www.leboncoin.fr/ad/ordinateurs/3226340061",
      "found_at": "2026-07-01",
      "note": "Correspond aux critères (M2 Ultra 64 Go / 1 To, ≤ 2520 €). À re-vérifier — l'annonce peut avoir expiré."
    }
  ]
}
